esp32_usb_gpio.py
esp32_usb_gpio-0.1.5.dist-info/METADATA
esp32_usb_gpio-0.1.5.dist-info/WHEEL
esp32_usb_gpio-0.1.5.dist-info/top_level.txt
esp32_usb_gpio-0.1.5.dist-info/RECORD
