Metadata-Version: 2.1
Name: esp32-usb-gpio
Version: 0.1.5
Summary: A Python library for controlling ESP32 GPIO pins via USB serial communication.
Home-page: https://github.com/aakash4895/ESP32-USB-GPIO-PY
Author: Aakash Singh
Author-email: aakash.singh4895@gmail.com
License: GPL-3.0-or-later
Keywords: esp32,gpio,usb,serial,communication,hardware,control
Classifier: Development Status :: 3 - Alpha
Classifier: Intended Audience :: Developers
Classifier: Topic :: Software Development :: Libraries :: Python Modules
Classifier: Topic :: System :: Hardware
Classifier: License :: OSI Approved :: GNU General Public License v3 or later (GPLv3+)
Classifier: Programming Language :: Python :: 3
Classifier: Programming Language :: Python :: 3.7
Classifier: Programming Language :: Python :: 3.8
Classifier: Programming Language :: Python :: 3.9
Classifier: Programming Language :: Python :: 3.10
Classifier: Programming Language :: Python :: 3.11
Classifier: Programming Language :: Python :: 3.12
Classifier: Operating System :: OS Independent
Requires-Python: >=3.7
Requires-Dist: pyserial
